<?xml version="1.0" encoding="UTF-8"?>
<settings xmlns="http://maven.apache.org/POM/4.0.0"
  xmlns:xsi="http://www.w3.org/2001/XMLSchema-instance"
  xsi:schemaLocation="http://maven.apache.org/POM/4.0.0 http://maven.apache.org/xsd/settings-4.0.0.xsd">
  <profiles>
    <profile>
      <id>jboss-community-repository</id>
      <repositories>
        <repository>
          <id>jboss-community-repository-group</id>
          <name>JBoss Community Repository Group</name>
          <url>https://repository.jboss.org/nexus/content/groups/public</url>
          <layout>default</layout>
          <releases>
            <enabled>true</enabled>
            <updatePolicy>never</updatePolicy>
          </releases>
          <snapshots>
            <enabled>true</enabled>
            <updatePolicy>never</updatePolicy>
          </snapshots>
        </repository>
      </repositories>
      <pluginRepositories>
        <pluginRepository>
          <id>jboss-community-repository-group</id>
          <name>JBoss Community Repository Group</name>
          <url>https://repository.jboss.org/nexus/content/groups/public</url>
          <layout>default</layout>
          <releases>
            <enabled>true</enabled>
            <updatePolicy>never</updatePolicy>
          </releases>
          <snapshots>
            <enabled>false</enabled>
            <updatePolicy>never</updatePolicy>
          </snapshots>
        </pluginRepository>
      </pluginRepositories>
    </profile>
  </profiles>
  <activeProfiles>
    <activeProfile>jboss-community-repository</activeProfile>
  </activeProfiles>
</settings>
